__init__.py
folium_express.py
folium_express-0.0.3.dist-info/LICENSE
folium_express-0.0.3.dist-info/METADATA
folium_express-0.0.3.dist-info/WHEEL
folium_express-0.0.3.dist-info/top_level.txt
folium_express-0.0.3.dist-info/RECORD
